strip_bom/__init__.py
strip_bom/core.py
strip_bom/py.typed
strip_bom-1.0.0.dist-info/METADATA
strip_bom-1.0.0.dist-info/WHEEL
strip_bom-1.0.0.dist-info/licenses/LICENSE
strip_bom-1.0.0.dist-info/RECORD
