Metadata-Version: 2.4
Name: strip-bom
Version: 1.0.0
Summary: Strip UTF-8 byte order mark (BOM) from strings, bytes, streams, and files. Inspired by the popular strip-bom npm package
Project-URL: Homepage, https://github.com/ysskrishna/strip-bom
Project-URL: Repository, https://github.com/ysskrishna/strip-bom.git
Project-URL: Issues, https://github.com/ysskrishna/strip-bom/issues
Project-URL: Changelog, https://github.com/ysskrishna/strip-bom/blob/main/CHANGELOG.md
Author-email: "Y. Siva Sai Krishna" <sivasaikrishnassk@gmail.com>
License: MIT
License-File: LICENSE
Keywords: bom,byte-order-mark,mit license,remove,strip,strip-bom,strip-bom-buf,strip-bom-stream,text-processing,unicode,utf-8,utilities,utils,ysskrishna
Classifier: Development Status :: 5 - Production/Stable
Classifier: Intended Audience :: Developers
Classifier: License :: OSI Approved :: MIT License
Classifier: Operating System :: OS Independent
Classifier: Programming Language :: Python :: 3
Classifier: Programming Language :: Python :: 3.8
Classifier: Programming Language :: Python :: 3.9
Classifier: Programming Language :: Python :: 3.10
Classifier: Programming Language :: Python :: 3.11
Classifier: Programming Language :: Python :: 3.12
Classifier: Topic :: Software Development :: Libraries :: Python Modules
Classifier: Topic :: Text Processing :: General
Classifier: Topic :: Utilities
Classifier: Typing :: Typed
Requires-Python: >=3.8
